pquant/__init__.py
pquant/_version.py
pquant/configs/__init__.py
pquant/configs/config_ap.yaml
pquant/configs/config_autosparse.yaml
pquant/configs/config_cs.yaml
pquant/configs/config_dst.yaml
pquant/configs/config_fitcompress.yaml
pquant/configs/config_mdmm.yaml
pquant/configs/config_pdp.yaml
pquant/configs/config_wanda.yaml
pquant/configs/finetuning.yaml
pquant/core/__init__.py
pquant/core/constants.py
pquant/core/finetuning.py
pquant/core/quantizer_functions.py
pquant/core/utils.py
pquant/core/keras/__init__.py
pquant/core/keras/activations.py
pquant/core/keras/layers.py
pquant/core/keras/quantizer.py
pquant/core/keras/train.py
pquant/core/torch/__init__.py
pquant/core/torch/activations.py
pquant/core/torch/fit_compress.py
pquant/core/torch/layers.py
pquant/core/torch/optimizers.py
pquant/core/torch/quantizer.py
pquant/core/torch/train.py
pquant/data_models/finetuning_model.py
pquant/data_models/fitcompress_model.py
pquant/data_models/pruning_model.py
pquant/data_models/quantization_model.py
pquant/data_models/training_model.py
pquant/pruning_methods/__init__.py
pquant/pruning_methods/activation_pruning.py
pquant/pruning_methods/autosparse.py
pquant/pruning_methods/constraint_functions.py
pquant/pruning_methods/cs.py
pquant/pruning_methods/dst.py
pquant/pruning_methods/fitcompress.py
pquant/pruning_methods/mdmm.py
pquant/pruning_methods/metric_functions.py
pquant/pruning_methods/pdp.py
pquant/pruning_methods/wanda.py
pquant_ml-0.0.3.dist-info/licenses/LICENSE
pquant_ml-0.0.3.dist-info/METADATA
pquant_ml-0.0.3.dist-info/WHEEL
pquant_ml-0.0.3.dist-info/top_level.txt
pquant_ml-0.0.3.dist-info/RECORD
