Metadata-Version: 2.4
Name: pquant-ml
Version: 0.0.3
Summary: Pruning and Quantization of ML models
Author: NGT 1.3 team
License: Apache-2.0
Project-URL: repository, https://github.com/nroope/PQuant
Classifier: Development Status :: 3 - Alpha
Classifier: Intended Audience :: Developers
Classifier: Intended Audience :: Science/Research
Classifier: License :: OSI Approved :: Apache Software License
Classifier: Programming Language :: Python :: 3 :: Only
Classifier: Programming Language :: Python :: 3.10
Classifier: Programming Language :: Python :: 3.11
Classifier: Programming Language :: Python :: 3.12
Classifier: Programming Language :: Python :: 3.13
Classifier: Topic :: Software Development :: Libraries :: Python Modules
Requires-Python: >=3.10
License-File: LICENSE
Requires-Dist: hgq2
Requires-Dist: keras>=3
Requires-Dist: optuna
Requires-Dist: pydantic>=2
Requires-Dist: pyyaml>=6.0.1
Requires-Dist: quantizers>=1.1
Provides-Extra: all
Requires-Dist: pytest>=8.4; extra == "all"
Requires-Dist: tensorflow<=2.20,>=2.17; extra == "all"
Requires-Dist: torch>=2.1; extra == "all"
Provides-Extra: tensorflow
Requires-Dist: tensorflow<=2.20,>=2.17; extra == "tensorflow"
Provides-Extra: test
Requires-Dist: pytest>=8.4; extra == "test"
Provides-Extra: torch
Requires-Dist: torch>=2.1; extra == "torch"
Dynamic: license-file
